d8analysis/__init__.py
d8analysis/__main__.py
d8analysis/container.py
d8analysis/data/__init__.py
d8analysis/data/credit.py
d8analysis/data/dataclass.py
d8analysis/data/dataset.py
d8analysis/data/entity.py
d8analysis/data/generation.py
d8analysis/data/plot.py
d8analysis/qualitative/__init__.py
d8analysis/quantitative/__init__.py
d8analysis/quantitative/descriptive/__init__.py
d8analysis/quantitative/descriptive/base.py
d8analysis/quantitative/descriptive/categorical.py
d8analysis/quantitative/descriptive/continuous.py
d8analysis/quantitative/descriptive/stats.py
d8analysis/quantitative/inferential/__init__.py
d8analysis/quantitative/inferential/base.py
d8analysis/quantitative/inferential/centrality/__init__.py
d8analysis/quantitative/inferential/centrality/ttest.py
d8analysis/quantitative/inferential/distribution/__init__.py
d8analysis/quantitative/inferential/distribution/kstest.py
d8analysis/quantitative/inferential/relational/__init__.py
d8analysis/quantitative/inferential/relational/chisquare.py
d8analysis/quantitative/inferential/relational/pearson.py
d8analysis/quantitative/inferential/relational/spearman.py
d8analysis/service/__init__.py
d8analysis/service/io.py
d8analysis/setup.py
d8analysis/visual/__init__.py
d8analysis/visual/base.py
d8analysis/visual/config.py
d8analysis/visual/seaborn/__init__.py
d8analysis/visual/seaborn/association.py
d8analysis/visual/seaborn/base.py
d8analysis/visual/seaborn/centrality.py
d8analysis/visual/seaborn/config.py
d8analysis/visual/seaborn/distribution.py
d8analysis/visual/seaborn/grid.py
d8analysis/visual/seaborn/plot.py
d8analysis-0.2.20.dist-info/WHEEL
d8analysis-0.2.20.dist-info/METADATA
d8analysis-0.2.20.dist-info/RECORD
